{
  "source": "exa",
  "name": "Accenture AI Leaders Podcast",
  "host": "",
  "description": "Artificial Intelligence (AI) Leaders Podcast Series | Accenture\n[Skip to main content] [Skip to footer] \n \n# Accenture AI Leaders Podcast\nTune in to hear AI leaders discuss industry trends, challenges and opportunities related to AI, data and cloud.\nSubscribe to the series:\n[\nListen on Apple Podcasts\n] [\nListen on Spotify\n] \n## Series episodes\nEpisodes (28)\nNewest to Oldest\n* Newest to Oldest\n* Oldest to Newest\nLoad more\n## Reinventing the future of business\n#### To listen to additional episodes",
  "rss_url": "",
  "website": "https://www.accenture.com/gb-en/services/applied-intelligence/ai-leaders-podcast-series",
  "language": "en",
  "categories": [],
  "last_episode_date": "",
  "episode_count": 0,
  "recent_episodes": [],
  "status": "discovered",
  "pursue": false,
  "notes": "",
  "discovered_date": "2026-02-18",
  "slug": "accenture-ai-leaders-podcast"
}